llm_explain/__init__.py
llm_explain/utils.py
llm_explain/data/__init__.py
llm_explain/data/samples.py
llm_explain/llm/__init__.py
llm_explain/llm/propose.py
llm_explain/llm/validate.py
llm_explain/models/__init__.py
llm_explain/models/cluster.py
llm_explain/models/diff.py
llm_explain/tests/__init__.py
llm_explain/tests/test_cluster.py
llm_explain/tests/test_diffs.py
llm_explain/tests/test_propose.py
llm_explain/tests/test_validate.py
llm_explain-0.1.1.dist-info/licenses/LICENSE
llm_explain-0.1.1.dist-info/METADATA
llm_explain-0.1.1.dist-info/WHEEL
llm_explain-0.1.1.dist-info/top_level.txt
llm_explain-0.1.1.dist-info/RECORD
