Metadata-Version: 2.4
Name: llm_explain
Version: 0.1.1
Summary: Tools that use LLM to explain datasets
Home-page: https://github.com/ruiqi-zhong/llm_explain
Author: Ruiqi Zhong
Author-email: Ruiqi Zhong <ruiqizhong1997@gmail.com>
License: MIT
Project-URL: Homepage, https://github.com/ruiqi-zhong/llm_explain
Project-URL: Repository, https://github.com/ruiqi-zhong/llm_explain
Requires-Python: >=3.9
License-File: LICENSE
Requires-Dist: openai
Requires-Dist: pydantic
Requires-Dist: requests
Requires-Dist: numpy
Requires-Dist: scikit-learn
Requires-Dist: tqdm
Dynamic: author
Dynamic: home-page
Dynamic: license-file
Dynamic: requires-python
